vending_machine.v
module vending_machine(
    output reg [8*30-1:0] LCD,
    output reg [8*30-1:0] money,
    output reg motor,
    input clk,
    input reset,
    input [1:0] select,
    input [1:0] coin,
    input dispense
);

    reg [3:0] current_state;
    reg [3:0] next_state;

    parameter idle = 4'b0000;
    parameter wait_10c = 4'b0001;
    parameter wait_20c = 4'b0010;
    parameter wait_30c = 4'b0011;
    parameter wait_40c = 4'b0100;
    parameter dispensing = 4'b0101;
    parameter return_money = 4'b0110;
    parameter insufficient = 4'b0111;
    parameter return_change = 4'b1000;
    parameter out_of_stock = 4'b1001;

    reg [7:0] product_price [3:0]; 
    reg [7:0] product_count [3:0]; 

    integer balance;
    integer change;

    initial begin
        product_price[0] = 10;
        product_price[1] = 20;
        product_price[2] = 30;
        product_price[3] = 40;

        product_count[0] = 4;
        product_count[1] = 2;
        product_count[2] = 2;
        product_count[3] = 0;
    end

    always @(posedge clk or posedge reset) begin
        if (reset) current_state <= idle;

        else begin
            case (current_state)
                default: current_state <= idle;
                idle: begin
                    if (product_count[select] > 0)
                        current_state <= next_state;
                    else
                        current_state <= out_of_stock;    
                end
                wait_10c, wait_20c, wait_30c, wait_40c, return_money, out_of_stock,
                    insufficient, return_change: current_state <= next_state;
                dispensing: begin
                    if (dispense == 1) begin
                        product_count[select] = product_count[select] - 1;
                        current_state <= next_state;
                    end
                    else
                        current_state <= dispensing;
                end
            endcase
        end
    end

    always @(current_state) begin
        case (current_state)
                default: current_state <= idle;
                idle: begin
                    LCD <= "idle";
                    money <= "0c";
                    motor <= 0;
                end
                wait_10c: begin
                    LCD <= "waiting for 10c";
                    money <= "0c";
                    motor <= 0;
                end
                wait_20c: begin
                    LCD <= "waiting for 20c";
                    money <= "0c";
                    motor <= 0;
                end
                wait_30c: begin
                    LCD <= "waiting for 30c";
                    money <= "0c";
                    motor <= 0;
                end
                wait_40c: begin
                    LCD <= "waiting for 40c";
                    money <= "0c";
                    motor <= 0;
                end
                return_change: begin
                    LCD <= "returning change";
                    begin 
                    balance = (coin == 2'b00) ? 10 :
                              (coin == 2'b01) ? 20 :
                              (coin == 2'b10) ? 50 :
                              (coin == 2'b11) ? 100 : 0;
                    end
                    change = balance - product_price[select];
                    money <= {"change: ", (change == 10) ? "10c" :
                        (change == 20) ? "20c" :
                        (change == 30) ? "30c" :
                        (change == 40) ? "40c" :
                        (change == 60) ? "60c" :
                        (change == 70) ? "70c" :
                        (change == 80) ? "80c" :
                        (change == 90) ? "90c" : "0c"};
                        motor <= 0;
                end
                return_money: begin
                    LCD <= "returning money";
                    money <= {"return amount: ", (coin == 2'b00) ? "10c" :
                        (coin == 2'b01) ? "20c" :
                        (coin == 2'b10) ? "50c" :
                        (coin == 2'b11) ? "100c" : "0c"}; 
                    motor <= 0;
                end
                insufficient: begin
                    LCD <= "insufficient";
                    begin 
                    balance = (coin == 2'b00) ? 10 :
                              (coin == 2'b01) ? 20 :
                              (coin == 2'b10) ? 50 :
                              (coin == 2'b11) ? 100 : 0;
                    end
                    change = product_price[select] - balance;
                    money <= {"needs: ", (change == 10) ? "10c" :
                        (change == 20) ? "20c" :
                        (change == 30) ? "30c" : "0c"};
                    motor <= 0;
                end
                out_of_stock: begin
                    LCD <= "out of stock";
                    money <= "ERROR";
                    motor <= 0;
                end
                dispensing: begin
                    LCD <= "dispensing";
                    money <= {"inserted amount: ", (product_price[select] == 10) ? "10c" :
                        (product_price[select] == 20) ? "20c" :
                        (product_price[select] == 30) ? "30c" :
                        (product_price[select] == 40) ? "40c" : "0c"}; 
                    motor <= 1;
                end
            endcase    
    end


    always @(current_state or select or coin or dispense) begin
        case(current_state)
            default: next_state = idle;
            idle: begin 
                    next_state = (select == 2'b00) ? wait_10c :
                        (select == 2'b01) ? wait_20c :
                        (select == 2'b10) ? wait_30c :
                        (select == 2'b11) ? wait_40c : idle;
                    end
            wait_10c: case(coin)
                2'b00: next_state = dispensing;
                2'b01: next_state = return_change;       
                2'b10, 2'b11: next_state = return_change; 
            endcase  
            wait_20c: case(coin)
                2'b00: next_state = insufficient;
                2'b01: next_state = dispensing;       
                2'b10, 2'b11: next_state = return_change; 
            endcase  
            wait_30c, wait_40c: case(coin)
                2'b00: next_state = insufficient;     
                2'b01: next_state = insufficient; 
                2'b10, 2'b11: next_state = return_change; 
            endcase
            return_change: next_state = dispensing;
            dispensing: next_state = ((dispense == 1) ? idle : dispensing);
            insufficient: next_state = return_money;
            return_money: next_state = idle;
            out_of_stock: next_state = idle;
        endcase
    end

endmodule

vending_machine_tb.v
`timescale 1s/1ms

`include "Azizi.Zahra.402243083.VendingMachine.v"

module vending_machine_tb();

    reg clk = 0;
    reg reset;
    reg [1:0] select;
    reg [1:0] coin;
    reg dispense;

    wire [8*30-1:0] LCD;
    wire [8*30-1:0] money;
    wire motor;

    vending_machine vm (
        .clk(clk),
        .reset(reset),
        .select(select),
        .coin(coin),
        .dispense(dispense),
        .LCD(LCD),
        .money(money),
        .motor(motor)
    );

    always begin
        #5 clk = ~clk;
    end

    initial begin

        $dumpfile("test_vm.vcd");
	$dumpvars(0, vending_machine_tb);
     
        dispense = 0;
        reset = 1;
        #10;
        $display("before tests\t Time: %0d | LCD: %s | money: %s | Motor: %b", 
                $time, LCD, money, motor);
        reset = 0;

        // Test 1: Select item 1 (price 10c) and insert 10c
        $display("Test 1------------------------------------------------------------------------------------------------------------");
        select = 2'b00;
        #10;
        $display("select p1\t Time: %0d | LCD: %s | money: %s | Motor: %b", 
                $time, LCD, money, motor);
        coin = 2'b00; 
        #10; 
        $display("insert 10c\t Time: %0d | LCD: %s | money: %s | Motor: %b", 
                $time, LCD, money, motor);
        #10;
        $display("dispense cont.\t Time: %0d | LCD: %s | money: %s | Motor: %b", 
                $time, LCD, money, motor);
        dispense = 1;
        #10
        $display("finished\t Time: %0d | LCD: %s | money: %s | Motor: %b", 
                $time, LCD, money, motor);

        // Test 2: Select item 2 (price 20c) and insert 20c
        $display("Test 2------------------------------------------------------------------------------------------------------------");
        select = 2'b01;
        #10;
        dispense = 0;
        $display("select p2\t Time: %0d | LCD: %s | money: %s | Motor: %b", 
                $time, LCD, money, motor);
        coin = 2'b01; 
        #10; 
        $display("insert 20c\t Time: %0d | LCD: %s | money: %s | Motor: %b", 
                $time, LCD, money, motor);
        dispense = 1;
        #10
        $display("finished\t Time: %0d | LCD: %s | money: %s | Motor: %b", 
                $time, LCD, money, motor);

        // Test 3: Select item 3 (price 30c) and insert 20c (insufficient)
        $display("Test 3------------------------------------------------------------------------------------------------------------");
        select = 2'b10;
        dispense = 0;
        #10;
        $display("select p3\t Time: %0d | LCD: %s | money: %s | Motor: %b", 
                $time, LCD, money, motor);
        coin = 2'b01; 
        #10; 
        $display("insert 20c\t Time: %0d | LCD: %s | money: %s | Motor: %b", 
                $time, LCD, money, motor);
        #10;
        $display("return money\t Time: %0d | LCD: %s | money: %s | Motor: %b", 
                $time, LCD, money, motor);
        #10;
        $display("finished\t Time: %0d | LCD: %s | money: %s | Motor: %b", 
                $time, LCD, money, motor);

        // Test 4: Select item 3 (price 30c) and insert 50c (return change)
        $display("Test 4------------------------------------------------------------------------------------------------------------");
        select = 2'b10;
        #10;
        $display("select p3\t Time: %0d | LCD: %s | money: %s | Motor: %b", 
                $time, LCD, money, motor);
        coin = 2'b10; 
        #10; 
        $display("insert 50c\t Time: %0d | LCD: %s | money: %s | Motor: %b", 
                $time, LCD, money, motor);
        dispense = 1;
        #10;
        $display("change returned\t Time: %0d | LCD: %s | money: %s | Motor: %b", 
                $time, LCD, money, motor);
        #10;
        $display("finished\t Time: %0d | LCD: %s | money: %s | Motor: %b", 
                $time, LCD, money, motor);

        // Test 5: Select item 4 (out of stock)
        $display("Test 5------------------------------------------------------------------------------------------------------------");
        select = 2'b11;
        dispense = 0;
        #10;
        $display("select p4\t Time: %0d | LCD: %s | money: %s | Motor: %b", 
                $time, LCD, money, motor);
        #10;
        $display("finished\t Time: %0d | LCD: %s | money: %s | Motor: %b", 
                $time, LCD, money, motor);

        //Test 6: Select item 3 then reset
        $display("Test 6------------------------------------------------------------------------------------------------------------");
        select = 2'b10;
        #10;
        $display("select p3.\t Time: %0d | LCD: %s | money: %s | Motor: %b", 
                $time, LCD, money, motor);
        reset = 1;
        #10;
        $display("after reset\t Time: %0d | LCD: %s | money: %s | Motor: %b", 
                $time, LCD, money, motor);
        reset = 0;

        // Test 7: Select item 2 until it is out of stock
        $display("Test 7------------------------------------------------------------------------------------------------------------");
        select = 2'b01;
        #10;
        dispense = 0;
        $display("select p2\t Time: %0d | LCD: %s | money: %s | Motor: %b", 
                $time, LCD, money, motor);
        coin = 2'b01; 
        #10; 
        $display("insert 20c\t Time: %0d | LCD: %s | money: %s | Motor: %b", 
                $time, LCD, money, motor);
        dispense = 1;
        #10
        $display("dispense fin.\t Time: %0d | LCD: %s | money: %s | Motor: %b", 
                $time, LCD, money, motor);

        select = 2'b01;
        #10;
        dispense = 0;
        $display("select p2\t Time: %0d | LCD: %s | money: %s | Motor: %b", 
                $time, LCD, money, motor);

        #100; 
        $display("Finish------------------------------------------------------------------------------------------------------------");
        $finish;
    end

endmodule

test_vm.vcd
$date
	Fri Jun 21 23:10:42 2024
$end
$version
	Icarus Verilog
$end
$timescale
	1ms
$end
$scope module vending_machine_tb $end
$var wire 1 ! motor $end
$var wire 240 " money [239:0] $end
$var wire 240 # LCD [239:0] $end
$var reg 1 $ clk $end
$var reg 2 % coin [1:0] $end
$var reg 1 & dispense $end
$var reg 1 ' reset $end
$var reg 2 ( select [1:0] $end
$scope module vm $end
$var wire 1 $ clk $end
$var wire 2 ) coin [1:0] $end
$var wire 1 & dispense $end
$var wire 1 ' reset $end
$var wire 2 * select [1:0] $end
$var reg 240 + LCD [239:0] $end
$var reg 4 , current_state [3:0] $end
$var reg 240 - money [239:0] $end
$var reg 1 ! motor $end
$var reg 4 . next_state [3:0] $end
$var integer 32 / balance [31:0] $end
$var integer 32 0 change [31:0] $end
$upscope $end
$upscope $end
$enddefinitions $end
#0
$dumpvars
bx 0
bx /
b0xxx .
b11000001100011 -
b0 ,
b1101001011001000110110001100101 +
bx *
bx )
bx (
1'
0&
bx %
0$
b1101001011001000110110001100101 #
b11000001100011 "
0!
$end
#5000
1$
#10000
b1 .
0$
b0 (
b0 *
0'
#15000
b11101110110000101101001011101000110100101101110011001110010000001100110011011110111001000100000001100010011000001100011 #
b11101110110000101101001011101000110100101101110011001110010000001100110011011110111001000100000001100010011000001100011 +
b1 ,
1$
#20000
b101 .
0$
b0 %
b0 )
#25000
1!
b110100101101110011100110110010101110010011101000110010101100100001000000110000101101101011011110111010101101110011101000011101000100000001100010011000001100011 "
b110100101101110011100110110010101110010011101000110010101100100001000000110000101101101011011110111010101101110011101000011101000100000001100010011000001100011 -
b1100100011010010111001101110000011001010110111001110011011010010110111001100111 #
b1100100011010010111001101110000011001010110111001110011011010010110111001100111 +
b101 ,
1$
#30000
0$
#35000
1$
#40000
b0 .
0$
1&
#45000
0!
b11000001100011 "
b11000001100011 -
b1101001011001000110110001100101 #
b1101001011001000110110001100101 +
b1 .
b0 ,
1$
#50000
b10 .
0$
b1 (
b1 *
#55000
b11101110110000101101001011101000110100101101110011001110010000001100110011011110111001000100000001100100011000001100011 #
b11101110110000101101001011101000110100101101110011001110010000001100110011011110111001000100000001100100011000001100011 +
b111 .
b10 ,
1$
#60000
b101 .
0$
b1 %
b1 )
0&
#65000
1!
b110100101101110011100110110010101110010011101000110010101100100001000000110000101101101011011110111010101101110011101000011101000100000001100100011000001100011 "
b110100101101110011100110110010101110010011101000110010101100100001000000110000101101101011011110111010101101110011101000011101000100000001100100011000001100011 -
b1100100011010010111001101110000011001010110111001110011011010010110111001100111 #
b1100100011010010111001101110000011001010110111001110011011010010110111001100111 +
b101 ,
1$
#70000
b0 .
0$
1&
#75000
0!
b11000001100011 "
b11000001100011 -
b1101001011001000110110001100101 #
b1101001011001000110110001100101 +
b10 .
b0 ,
1$
#80000
b11 .
0$
0&
b10 (
b10 *
#85000
b11101110110000101101001011101000110100101101110011001110010000001100110011011110111001000100000001100110011000001100011 #
b11101110110000101101001011101000110100101101110011001110010000001100110011011110111001000100000001100110011000001100011 +
b111 .
b11 ,
1$
#90000
0$
#95000
b1101110011001010110010101100100011100110011101000100000001100010011000001100011 "
b1101110011001010110010101100100011100110011101000100000001100010011000001100011 -
b11010010110111001110011011101010110011001100110011010010110001101101001011001010110111001110100 #
b11010010110111001110011011101010110011001100110011010010110001101101001011001010110111001110100 +
b110 .
b1010 0
b10100 /
b111 ,
1$
#100000
0$
#105000
b1110010011001010111010001110101011100100110111000100000011000010110110101101111011101010110111001110100001110100010000000000000001100100011000001100011 "
b1110010011001010111010001110101011100100110111000100000011000010110110101101111011101010110111001110100001110100010000000000000001100100011000001100011 -
b11100100110010101110100011101010111001001101110011010010110111001100111001000000110110101101111011011100110010101111001 #
b11100100110010101110100011101010111001001101110011010010110111001100111001000000110110101101111011011100110010101111001 +
b0 .
b110 ,
1$
#110000
0$
#115000
b11000001100011 "
b11000001100011 -
b1101001011001000110110001100101 #
b1101001011001000110110001100101 +
b11 .
b0 ,
1$
#120000
0$
#125000
b11101110110000101101001011101000110100101101110011001110010000001100110011011110111001000100000001100110011000001100011 #
b11101110110000101101001011101000110100101101110011001110010000001100110011011110111001000100000001100110011000001100011 +
b111 .
b11 ,
1$
#130000
b1000 .
0$
b10 %
b10 )
#135000
b110001101101000011000010110111001100111011001010011101000100000001100100011000001100011 "
b110001101101000011000010110111001100111011001010011101000100000001100100011000001100011 -
b1110010011001010111010001110101011100100110111001101001011011100110011100100000011000110110100001100001011011100110011101100101 #
b1110010011001010111010001110101011100100110111001101001011011100110011100100000011000110110100001100001011011100110011101100101 +
b101 .
b10100 0
b110010 /
b1000 ,
1$
#140000
0$
1&
#145000
1!
b110100101101110011100110110010101110010011101000110010101100100001000000110000101101101011011110111010101101110011101000011101000100000001100110011000001100011 "
b110100101101110011100110110010101110010011101000110010101100100001000000110000101101101011011110111010101101110011101000011101000100000001100110011000001100011 -
b1100100011010010111001101110000011001010110111001110011011010010110111001100111 #
b1100100011010010111001101110000011001010110111001110011011010010110111001100111 +
b0 .
b101 ,
1$
#150000
0$
#155000
0!
b11000001100011 "
b11000001100011 -
b1101001011001000110110001100101 #
b1101001011001000110110001100101 +
b11 .
b0 ,
1$
#160000
b100 .
0$
0&
b11 (
b11 *
#165000
b100010101010010010100100100111101010010 "
b100010101010010010100100100111101010010 -
b11011110111010101110100001000000110111101100110001000000111001101110100011011110110001101101011 #
b11011110111010101110100001000000110111101100110001000000111001101110100011011110110001101101011 +
b0 .
b1001 ,
1$
#170000
0$
#175000
b11000001100011 "
b11000001100011 -
b1101001011001000110110001100101 #
b1101001011001000110110001100101 +
b100 .
b0 ,
1$
#180000
b11 .
0$
b10 (
b10 *
#185000
b11101110110000101101001011101000110100101101110011001110010000001100110011011110111001000100000001100110011000001100011 #
b11101110110000101101001011101000110100101101110011001110010000001100110011011110111001000100000001100110011000001100011 +
b1000 .
b11 ,
1$
#190000
b1101001011001000110110001100101 #
b1101001011001000110110001100101 +
b11 .
b0 ,
0$
1'
#195000
1$
#200000
b10 .
0$
b1 (
b1 *
0'
#205000
b11101110110000101101001011101000110100101101110011001110010000001100110011011110111001000100000001100100011000001100011 #
b11101110110000101101001011101000110100101101110011001110010000001100110011011110111001000100000001100100011000001100011 +
b1000 .
b10 ,
1$
#210000
b101 .
0$
b1 %
b1 )
#215000
1!
b110100101101110011100110110010101110010011101000110010101100100001000000110000101101101011011110111010101101110011101000011101000100000001100100011000001100011 "
b110100101101110011100110110010101110010011101000110010101100100001000000110000101101101011011110111010101101110011101000011101000100000001100100011000001100011 -
b1100100011010010111001101110000011001010110111001110011011010010110111001100111 #
b1100100011010010111001101110000011001010110111001110011011010010110111001100111 +
b101 ,
1$
#220000
b0 .
0$
1&
#225000
0!
b11000001100011 "
b11000001100011 -
b1101001011001000110110001100101 #
b1101001011001000110110001100101 +
b10 .
b0 ,
1$
#230000
0$
#235000
b100010101010010010100100100111101010010 "
b100010101010010010100100100111101010010 -
b11011110111010101110100001000000110111101100110001000000111001101110100011011110110001101101011 #
b11011110111010101110100001000000110111101100110001000000111001101110100011011110110001101101011 +
b0 .
b1001 ,
1$
#240000
0$
0&
#245000
b11000001100011 "
b11000001100011 -
b1101001011001000110110001100101 #
b1101001011001000110110001100101 +
b10 .
b0 ,
1$
#250000
0$
#255000
b100010101010010010100100100111101010010 "
b100010101010010010100100100111101010010 -
b11011110111010101110100001000000110111101100110001000000111001101110100011011110110001101101011 #
b11011110111010101110100001000000110111101100110001000000111001101110100011011110110001101101011 +
b0 .
b1001 ,
1$
#260000
0$
#265000
b11000001100011 "
b11000001100011 -
b1101001011001000110110001100101 #
b1101001011001000110110001100101 +
b10 .
b0 ,
1$
#270000
0$
#275000
b100010101010010010100100100111101010010 "
b100010101010010010100100100111101010010 -
b11011110111010101110100001000000110111101100110001000000111001101110100011011110110001101101011 #
b11011110111010101110100001000000110111101100110001000000111001101110100011011110110001101101011 +
b0 .
b1001 ,
1$
#280000
0$
#285000
b11000001100011 "
b11000001100011 -
b1101001011001000110110001100101 #
b1101001011001000110110001100101 +
b10 .
b0 ,
1$
#290000
0$
#295000
b100010101010010010100100100111101010010 "
b100010101010010010100100100111101010010 -
b11011110111010101110100001000000110111101100110001000000111001101110100011011110110001101101011 #
b11011110111010101110100001000000110111101100110001000000111001101110100011011110110001101101011 +
b0 .
b1001 ,
1$
#300000
0$
#305000
b11000001100011 "
b11000001100011 -
b1101001011001000110110001100101 #
b1101001011001000110110001100101 +
b10 .
b0 ,
1$
#310000
0$
#315000
b100010101010010010100100100111101010010 "
b100010101010010010100100100111101010010 -
b11011110111010101110100001000000110111101100110001000000111001101110100011011110110001101101011 #
b11011110111010101110100001000000110111101100110001000000111001101110100011011110110001101101011 +
b0 .
b1001 ,
1$
#320000
0$
#325000
b11000001100011 "
b11000001100011 -
b1101001011001000110110001100101 #
b1101001011001000110110001100101 +
b10 .
b0 ,
1$
#330000
0$
#335000
b100010101010010010100100100111101010010 "
b100010101010010010100100100111101010010 -
b11011110111010101110100001000000110111101100110001000000111001101110100011011110110001101101011 #
b11011110111010101110100001000000110111101100110001000000111001101110100011011110110001101101011 +
b0 .
b1001 ,
1$
